pyuow/__init__.py
pyuow/clock.py
pyuow/context/__init__.py
pyuow/context/base.py
pyuow/context/datapoint/__init__.py
pyuow/context/datapoint/aio/__init__.py
pyuow/context/datapoint/aio/base.py
pyuow/context/datapoint/aio/in_memory/__init__.py
pyuow/context/datapoint/aio/in_memory/impl.py
pyuow/context/datapoint/base.py
pyuow/context/datapoint/in_memory/__init__.py
pyuow/context/datapoint/in_memory/impl.py
pyuow/context/domain/__init__.py
pyuow/context/domain/base.py
pyuow/context/exceptions.py
pyuow/contrib/__init__.py
pyuow/contrib/sqlalchemy/__init__.py
pyuow/contrib/sqlalchemy/aio/__init__.py
pyuow/contrib/sqlalchemy/aio/repository/__init__.py
pyuow/contrib/sqlalchemy/aio/repository/base.py
pyuow/contrib/sqlalchemy/aio/work/__init__.py
pyuow/contrib/sqlalchemy/aio/work/impl.py
pyuow/contrib/sqlalchemy/repository/__init__.py
pyuow/contrib/sqlalchemy/repository/base.py
pyuow/contrib/sqlalchemy/tables/__init__.py
pyuow/contrib/sqlalchemy/tables/base.py
pyuow/contrib/sqlalchemy/work/__init__.py
pyuow/contrib/sqlalchemy/work/impl.py
pyuow/datapoint/__init__.py
pyuow/datapoint/aio/__init__.py
pyuow/datapoint/aio/base.py
pyuow/datapoint/aio/impl.py
pyuow/datapoint/base.py
pyuow/datapoint/exceptions.py
pyuow/datapoint/impl.py
pyuow/domain/__init__.py
pyuow/domain/aio/__init__.py
pyuow/domain/aio/event/__init__.py
pyuow/domain/aio/event/dist.py
pyuow/domain/base.py
pyuow/domain/event/__init__.py
pyuow/domain/event/base.py
pyuow/domain/event/dist.py
pyuow/entity/__init__.py
pyuow/entity/base.py
pyuow/py.typed
pyuow/repository/__init__.py
pyuow/repository/aio/__init__.py
pyuow/repository/aio/base.py
pyuow/repository/aio/domain.py
pyuow/repository/base.py
pyuow/repository/domain.py
pyuow/result/__init__.py
pyuow/result/exceptions.py
pyuow/result/impl.py
pyuow/types.py
pyuow/unit/__init__.py
pyuow/unit/aio/__init__.py
pyuow/unit/aio/base.py
pyuow/unit/aio/impl.py
pyuow/unit/base.py
pyuow/unit/exceptions.py
pyuow/unit/impl.py
pyuow/work/__init__.py
pyuow/work/aio/__init__.py
pyuow-0.8.0.dist-info/METADATA
pyuow-0.8.0.dist-info/WHEEL
pyuow-0.8.0.dist-info/licenses/LICENSE
pyuow-0.8.0.dist-info/RECORD
