Metadata-Version: 2.4
Name: pyuow
Version: 0.8.0
Summary: Python custom implementation of unit of work pattern
License: MIT
License-File: LICENSE
Author: SMAD
Maintainer: Sviatoslav Mosorko
Maintainer-email: slavikmosorko@gmail.com
Requires-Python: >=3.9,<4.0
Classifier: Development Status :: 5 - Production/Stable
Classifier: Intended Audience :: Developers
Classifier: License :: OSI Approved :: MIT License
Classifier: Natural Language :: English
Classifier: Operating System :: OS Independent
Classifier: Programming Language :: Python
Classifier: Programming Language :: Python :: 3
Classifier: Programming Language :: Python :: 3.9
Classifier: Programming Language :: Python :: 3.10
Classifier: Programming Language :: Python :: 3.11
Classifier: Programming Language :: Python :: 3.12
Classifier: Programming Language :: Python :: 3.13
Classifier: Programming Language :: Python :: 3.14
Classifier: Programming Language :: Python :: 3 :: Only
Classifier: Topic :: Software Development :: Libraries
Provides-Extra: sqlalchemy
Requires-Dist: sqlalchemy (>=2.0.44,<3.0.0) ; extra == "sqlalchemy"
Project-URL: Changelog, https://github.com/S-M-A-D/PyUoW/releases
Project-URL: Homepage, https://github.com/S-M-A-D/PyUoW
Project-URL: Repository, https://github.com/S-M-A-D/PyUoW
Project-URL: Tracker, https://github.com/S-M-A-D/PyUoW/issues
